{
    "area": {
        "id": 2163,
        "name": "Netherlands",
        "code": "NLD",
        "flag": "https://crests.football-data.org/8601.svg"
    },
    "competition": {
        "id": 2003,
        "name": "Eredivisie",
        "code": "DED",
        "type": "LEAGUE",
        "emblem": "https://crests.football-data.org/ED.png"
    },
    "season": {
        "id": 2400,
        "startDate": "2025-08-08",
        "endDate": "2026-05-17",
        "currentMatchday": 27,
        "winner": null
    },
    "id": 537441,
    "utcDate": "2025-08-08T18:00:00Z",
    "status": "FINISHED",
    "venue": null,
    "matchday": 1,
    "stage": "REGULAR_SEASON",
    "group": null,
    "lastUpdated": "2026-03-13T00:21:01Z",
    "homeTeam": {
        "id": 1920,
        "name": "Fortuna Sittard",
        "shortName": "Sittard",
        "tla": "SIT",
        "crest": "https://crests.football-data.org/1920.png"
    },
    "awayTeam": {
        "id": 718,
        "name": "Go Ahead Eagles",
        "shortName": "Go Ahead",
        "tla": "GOA",
        "crest": "https://crests.football-data.org/718.png"
    },
    "score": {
        "winner": "DRAW",
        "duration": "REGULAR",
        "fullTime": {
            "home": 2,
            "away": 2
        },
        "halfTime": {
            "home": 1,
            "away": 1
        }
    },
    "odds": {
        "msg": "Activate Odds-Package in User-Panel to retrieve odds."
    },
    "referees": [
        {
            "id": 17141,
            "name": "Rob Dieperink",
            "type": "REFEREE",
            "nationality": "Netherlands"
        }
    ]
}
